Harmonics/__init__.py
Harmonics/hypo_test.py
Harmonics/model.py
Harmonics/utils.py
harmonics_bio-0.0.4.dist-info/LICENSE
harmonics_bio-0.0.4.dist-info/METADATA
harmonics_bio-0.0.4.dist-info/WHEEL
harmonics_bio-0.0.4.dist-info/top_level.txt
harmonics_bio-0.0.4.dist-info/RECORD
