Metadata-Version: 2.1
Name: harmonics-bio
Version: 0.0.4
Summary: Hierarchical distribution matching enables comprehensive characterization of common and condition-specific cell niches in spatial omics data
Home-page: https://github.com/YangLabHKUST/Harmonics
Author: Yuyao Liu
Author-email: yliuow@connect.ust.hk
License: MIT
License-File: LICENSE
Requires-Dist: numpy
Requires-Dist: pandas
Requires-Dist: anndata
Requires-Dist: scipy
Requires-Dist: matplotlib
Requires-Dist: scikit-learn
Requires-Dist: statsmodels
Requires-Dist: numba
Requires-Dist: tqdm
